Bootini_Star-0.0.7.dev1.data/data/Bootini-Star/LICENSE
Bootini_Star-0.0.7.dev1.data/data/Bootini-Star/db-helper.sh
Bootini_Star-0.0.7.dev1.data/data/Bootini-Star/groups.json.bz2
Bootini_Star-0.0.7.dev1.data/data/Bootini-Star/types.json.bz2
Bootini_Star-0.0.7.dev1.data/data/Bootini-Star/wsgi.py
Bootini_Star-0.0.7.dev1.dist-info/METADATA
Bootini_Star-0.0.7.dev1.dist-info/RECORD
Bootini_Star-0.0.7.dev1.dist-info/WHEEL
Bootini_Star-0.0.7.dev1.dist-info/top_level.txt
bootini_star/__init__.py
bootini_star/account_views.py
bootini_star/config.py
bootini_star/email.py
bootini_star/esi.py
bootini_star/extensions.py
bootini_star/forms.py
bootini_star/models.py
bootini_star/resource_views.py
bootini_star/sso.py
bootini_star/sso_views.py
bootini_star/version.py
bootini_star/views.py
swagger_client/__init__.py
swagger_client/api_client.py
swagger_client/configuration.py
swagger_client/rest.py
swagger_client/api/__init__.py
swagger_client/api/alliance_api.py
swagger_client/api/assets_api.py
swagger_client/api/bookmarks_api.py
swagger_client/api/calendar_api.py
swagger_client/api/character_api.py
swagger_client/api/clones_api.py
swagger_client/api/contacts_api.py
swagger_client/api/contracts_api.py
swagger_client/api/corporation_api.py
swagger_client/api/dogma_api.py
swagger_client/api/faction_warfare_api.py
swagger_client/api/fittings_api.py
swagger_client/api/fleets_api.py
swagger_client/api/incursions_api.py
swagger_client/api/industry_api.py
swagger_client/api/insurance_api.py
swagger_client/api/killmails_api.py
swagger_client/api/location_api.py
swagger_client/api/loyalty_api.py
swagger_client/api/mail_api.py
swagger_client/api/market_api.py
swagger_client/api/opportunities_api.py
swagger_client/api/planetary_interaction_api.py
swagger_client/api/routes_api.py
swagger_client/api/search_api.py
swagger_client/api/skills_api.py
swagger_client/api/sovereignty_api.py
swagger_client/api/status_api.py
swagger_client/api/universe_api.py
swagger_client/api/user_interface_api.py
swagger_client/api/wallet_api.py
swagger_client/api/wars_api.py
swagger_client/models/__init__.py
