Metadata-Version: 2.1
Name: Bootini-Star
Version: 0.0.7.dev1
Summary: Inspect EVE Online mail and skill queues in a web browser.
Home-page: https://github.com/rseichter/bootini-star.git
Author: Ralph Seichter
Author-email: bootini-star@seichter.de
License: MIT
Project-URL: Source, https://github.com/rseichter/bootini-star.git
Platform: UNKNOWN
Classifier: License :: OSI Approved :: MIT License
Classifier: Development Status :: 3 - Alpha
Classifier: Programming Language :: Python :: 3.4
Classifier: Intended Audience :: Developers
Requires-Python: >=3.6
Requires-Dist: Flask (>=1.0.2)
Requires-Dist: Flask-Bootstrap4 (>=4.0.2)
Requires-Dist: Flask-Login (>=0.4.1)
Requires-Dist: Flask-WTF (>=0.14.2)
Requires-Dist: passlib (>=1.7.1)
Requires-Dist: pymongo (>=3.6.1)
Requires-Dist: requests-oauthlib (>=0.8.0)
Requires-Dist: Werkzeug (>=0.14.1)
